{
  "id": "1877110",
  "name": "sportPlay",
  "font_family": "iconfont",
  "css_prefix_text": "icon-",
  "description": "",
  "glyphs": [
    {
      "icon_id": "435924",
      "name": "卡路里",
      "font_class": "qialuli",
      "unicode": "e7b4",
      "unicode_decimal": 59316
    },
    {
      "icon_id": "954024",
      "name": "列表",
      "font_class": "liebiao",
      "unicode": "e61b",
      "unicode_decimal": 58907
    },
    {
      "icon_id": "7898688",
      "name": "管理员",
      "font_class": "guanliyuan",
      "unicode": "e600",
      "unicode_decimal": 58880
    },
    {
      "icon_id": "1554898",
      "name": "登陆",
      "font_class": "denglu",
      "unicode": "e606",
      "unicode_decimal": 58886
    },
    {
      "icon_id": "13871959",
      "name": "登陆密码",
      "font_class": "denglumima",
      "unicode": "e634",
      "unicode_decimal": 58932
    }
  ]
}
